setup.py
icoFlux/__init__.py
icoFlux/embedded.py
icoFlux.egg-info/PKG-INFO
icoFlux.egg-info/SOURCES.txt
icoFlux.egg-info/dependency_links.txt
icoFlux.egg-info/entry_points.txt
icoFlux.egg-info/requires.txt
icoFlux.egg-info/top_level.txt
icoFlux.egg-info/zip-safe
icoFlux/r1_4_1_dev/__init__.py
icoFlux/r1_5/__init__.py
icoFlux/r1_5_dev/__init__.py
icoFlux/r1_6/__init__.py
icoFlux/r1_6_dev/__init__.py
icoFlux/r2_0_0/__init__.py